[
  {
    "inputs": [],
    "name": "DISCOUNT_RATE",
    "outputs": [{ "internalType": "uint256", "name": "", "type": "uint256" }],
    "stateMutability": "view",
    "type": "function"
  },
  {
    "inputs": [],
    "name": "GHO_DISCOUNTED_PER_DISCOUNT_TOKEN",
    "outputs": [{ "internalType": "uint256", "name": "", "type": "uint256" }],
    "stateMutability": "view",
    "type": "function"
  },
  {
    "inputs": [],
    "name": "MIN_DEBT_TOKEN_BALANCE",
    "outputs": [{ "internalType": "uint256", "name": "", "type": "uint256" }],
    "stateMutability": "view",
    "type": "function"
  },
  {
    "inputs": [],
    "name": "MIN_DISCOUNT_TOKEN_BALANCE",
    "outputs": [{ "internalType": "uint256", "name": "", "type": "uint256" }],
    "stateMutability": "view",
    "type": "function"
  },
  {
    "inputs": [
      { "internalType": "uint256", "name": "debtBalance", "type": "uint256" },
      { "internalType": "uint256", "name": "discountTokenBalance", "type": "uint256" }
    ],
    "name": "calculateDiscountRate",
    "outputs": [{ "internalType": "uint256", "name": "", "type": "uint256" }],
    "stateMutability": "pure",
    "type": "function"
  }
]
